simes/__init__.py
simes-0.1.4.dist-info/LICENSE
simes-0.1.4.dist-info/METADATA
simes-0.1.4.dist-info/WHEEL
simes-0.1.4.dist-info/top_level.txt
simes-0.1.4.dist-info/RECORD
