Metadata-Version: 2.1
Name: simes
Version: 0.1.4
Summary: simes, simple encrypted socket
Home-page: https://github.com/PabloIbannez/simes
Author-email: Pablo Ibáñez-Freire <p.ibanez.fre@gmail.com>
License: MIT License
Classifier: Development Status :: 5 - Production/Stable
Classifier: License :: OSI Approved :: MIT License
Classifier: Programming Language :: Python :: 3
Classifier: Programming Language :: Python :: 3.6
Classifier: Programming Language :: Python :: 3.7
Classifier: Programming Language :: Python :: 3.8
Classifier: Programming Language :: Python :: 3.9
Requires-Python: >=3.6
License-File: LICENSE
